Metadata-Version: 1.1
Name: litereval
Version: 0.0.6
Summary: Wrapper around ast.literal_eval with new {foo='bar', key=None} dict syntax.
Home-page: https://github.com/kiwi0fruit/litereval
Author: Peter Zagubisalo
Author-email: peter.zagubisalo@gmail.com
License: MIT
Platform: UNKNOWN
Classifier: Development Status :: 3 - Alpha
Classifier: Intended Audience :: Developers
Classifier: Topic :: Software Development :: Build Tools
Classifier: License :: OSI Approved :: MIT License
Classifier: Programming Language :: Python :: 3
Classifier: Programming Language :: Python :: 3.5
Classifier: Programming Language :: Python :: 3.6
